pythonic_cache/__init__.py
pythonic_cache/client.py
pythonic_cache/py.typed
pythonic_cache/integrations/__init__.py
pythonic_cache/integrations/fastapi.py
pythonic_cache/integrations/flask.py
pythonic_cache/storage/__init__.py
pythonic_cache/storage/base.py
pythonic_cache/storage/memory.py
pythonic_cache/storage/redis.py
pythonic_cache/storage/utils.py
pythonic_cache-0.4.0.dist-info/LICENSE.md
pythonic_cache-0.4.0.dist-info/METADATA
pythonic_cache-0.4.0.dist-info/WHEEL
pythonic_cache-0.4.0.dist-info/top_level.txt
pythonic_cache-0.4.0.dist-info/RECORD
