Metadata-Version: 2.1
Name: pythonic-cache
Version: 0.4.0
Summary: Pythonic-cache library for caching, which has everything you need out of the box and nothing extra.
Author-email: Alim Abrekov <alimabrekov@outlook.com>
Project-URL: Bug Tracker, https://github.com/Dark04072006/pythonic-cache/issues
Project-URL: Homepage, https://github.com/Dark04072006/pythonic-cache
Classifier: Programming Language :: Python :: 3
Classifier: License :: OSI Approved :: MIT License
Classifier: Operating System :: OS Independent
Requires-Python: >=3.11.0
License-File: LICENSE.md
Provides-Extra: fastapi
Requires-Dist: fastapi >=0.110.2 ; extra == 'fastapi'
Provides-Extra: flask
Requires-Dist: flask >=3.0.3 ; extra == 'flask'
Provides-Extra: lint
Requires-Dist: black >=24.3.0 ; extra == 'lint'
Requires-Dist: isort >=5.13.2 ; extra == 'lint'
Requires-Dist: mypy >=1.9.0 ; extra == 'lint'
Requires-Dist: flake8 >=7.0.0 ; extra == 'lint'
Requires-Dist: flake8-pyproject >=1.2.3 ; extra == 'lint'
Provides-Extra: testing
Requires-Dist: pytest >=8.1.1 ; extra == 'testing'
Requires-Dist: pytest-asyncio >=0.23.6 ; extra == 'testing'
Requires-Dist: httpx >=0.27.0 ; extra == 'testing'
